hedeut/__init__.py
hedeut-0.1.dev0.dist-info/METADATA
hedeut-0.1.dev0.dist-info/WHEEL
hedeut-0.1.dev0.dist-info/licenses/LICENSE
hedeut-0.1.dev0.dist-info/RECORD
