Metadata-Version: 2.1
Name: hedeut
Version: 0.1.dev0
Summary: HElpful DEcorators and UTilities for working with JAX.
Project-URL: Repository, https://github.com/dimasad/hedeut
Author-email: Dimas Abreu Archanjo Dutra <dimas.dutra@mail.wvu.edu>
License: MIT License
License-File: LICENSE
Requires-Python: >=3.10
Requires-Dist: jax
Requires-Dist: numpy
